{
	"name": "ctov:pillager_outpost/jungle/deco",
	"fallback": "ctov:pillager_outpost/common/mobs",
	"elements": [
		{
			"weight": 1,
			"element": {
				"element_type": "minecraft:single_pool_element",
				"projection": "rigid",
				"location": "ctov:pillager_outpost/jungle/deco/cage",
				"processors": "minecraft:empty"
			}
		},
		{
			"weight": 1,
			"element": {
				"element_type": "minecraft:single_pool_element",
				"projection": "rigid",
				"location": "ctov:pillager_outpost/jungle/deco/campfire",
				"processors": "minecraft:empty"
			}
		},
		{
			"weight": 1,
			"element": {
				"element_type": "minecraft:single_pool_element",
				"projection": "rigid",
				"location": "ctov:pillager_outpost/jungle/deco/golem_cage",
				"processors": "minecraft:empty"
			}
		},
		{
			"weight": 1,
			"element": {
				"element_type": "minecraft:single_pool_element",
				"projection": "rigid",
				"location": "ctov:pillager_outpost/jungle/deco/kitchen",
				"processors": "minecraft:empty"
			}
		},
		{
			"weight": 1,
			"element": {
				"element_type": "minecraft:single_pool_element",
				"projection": "rigid",
				"location": "ctov:pillager_outpost/jungle/deco/ravager_pen",
				"processors": "minecraft:empty"
			}
		},
		{
			"weight": 1,
			"element": {
				"element_type": "minecraft:single_pool_element",
				"projection": "rigid",
				"location": "ctov:pillager_outpost/jungle/deco/smith",
				"processors": "minecraft:empty"
			}
		},
		{
			"weight": 1,
			"element": {
				"element_type": "minecraft:single_pool_element",
				"projection": "rigid",
				"location": "ctov:pillager_outpost/jungle/deco/target",
				"processors": "minecraft:empty"
			}
		},
		{
			"weight": 1,
			"element": {
				"element_type": "minecraft:single_pool_element",
				"projection": "rigid",
				"location": "ctov:pillager_outpost/jungle/deco/tent",
				"processors": "minecraft:empty"
			}
		},
		{
			"weight": 1,
			"element": {
				"element_type": "minecraft:single_pool_element",
				"projection": "rigid",
				"location": "ctov:pillager_outpost/jungle/deco/villager_cage",
				"processors": "minecraft:empty"
			}
		},
		{
			"weight": 1,
			"element": {
				"element_type": "minecraft:single_pool_element",
				"projection": "rigid",
				"location": "ctov:pillager_outpost/jungle/deco/allay_cage",
				"processors": "minecraft:empty"
			}
		}
	]
}