{
	"type": "lithostitched:add_template_pool_elements",
	"predicate": {
		"type": "lithostitched:any_of",
			"predicates": [
			{
				"type": "lithostitched:mod_loaded",
				"mod_id": "byg"
			},
			{
				"type": "lithostitched:mod_loaded",
				"mod_id": "biomeswevegone"
			}
		]
	},
	"template_pools": "ctov:village/taiga_fortified/house",
	"elements": [
		{
			"weight": 5,
			"element": {
				"element_type": "minecraft:single_pool_element",
				"projection": "rigid",
				"processors": "ctov:village/taiga_fortified/house",
				"location":"ctov:village/taiga_fortified/jobsite/forager"
			}
		}
	]
}